{
    "type": "machine_model",
    "name": "BBL-3DP-V4NORMAL",
    "url": "http://www.bambulab.com/Parameters/printer_model/BBL-3DP-V4NORMAL.json",
    "nozzle_diameter": "0.4",
    "machine_tech": "FFF",
    "family": "BBL-3DP",
    "bed_model": "bbl-3dp-004_bed.stl",
    "bed_texture": "bbl-3dp-001.svg",
    "default_materials": "Generic PLA;PolyDissolve;PolyFlex TPU95HF;K5 Sparkle PLA;Rock PLA;Generic TPU95;Generic TPU90;Generic TPU87;Generic TPU83;PolyMide CoPA;PolyMide PA6-GF;PolyMide PA12-CF;PolyMide PA6-CF;PolyLite ASA;K5 ASA;K5T ABS;ALL PLA EXP.Silk;ALL PLA Silk;PolyTerra PLA~; PolyLite PLA~; PolyLite PLA Pro~; PolyLite PLA Silk~; PolyMax PLA~; PolyWood PLA~;K5 Silk PLA~;K5 PLA~;K6 PLA~;K6CF PLA~;K5M PLA~;K5P PLA~;eSUN PLA; eSUN PLA+~; eSUN PLA Matte~; eSUN PLA Silk~; eSUN PLA ST; PolyLite ABS; K5 ABS; eSUN ABS; eSUN ABS+; K5 PETG; K6 PETG; PolyMax PETG; PolyLite PETG; eSUN PETG; PolySupport;K7CF PET;K7CFLM PAHT; BBL PA-CF;K7 PC; PolyLite PC; PolyMax PC;"
}