{
    "type": "filament",
    "name": "Generic PCTG @BBL H2C 0.4 nozzle",
    "inherits": "Generic PCTG @base",
    "from": "system",
    "setting_id": "GFSG97_08",
    "instantiation": "true",
    "filament_cooling_before_tower": [
        "10",
        "10"
    ],
    "filament_max_volumetric_speed": [
        "6",
        "6"
    ],
    "filament_prime_volume": [
        "30"
    ],
    "filament_prime_volume_nc": [
        "30"
    ],
    "filament_pre_cooling_temperature_nc": [
        "215",
        "215"
    ],
    "filament_ramming_travel_time": [
        "0",
        "0"
    ],
    "filament_ramming_travel_time_nc": [
        "1",
        "1"
    ],
    "filament_change_length": [
        "4"
    ],
    "first_x_layer_fan_speed": [
        "0"
    ],
    "filament_change_length_nc": [
        "4"
    ],
    "include": [
        "fdm_filament_template_direct_dual"
    ],
    "nozzle_temperature": [
        "255",
        "255"
    ],
    "nozzle_temperature_initial_layer": [
        "255",
        "255"
    ],
    "temperature_vitrification": [
        "60"
    ],
    "compatible_printers": [
        "Bambu Lab H2C 0.4 nozzle"
    ],
    "filament_start_gcode": [
        "; filament start gcode\n"
    ],
    "filament_end_gcode": [
        "; filament end gcode \n"
    ]
}